closeio_api/__init__.py
closeio_api/utils.py
closeio-2.1.dist-info/LICENSE
closeio-2.1.dist-info/METADATA
closeio-2.1.dist-info/WHEEL
closeio-2.1.dist-info/top_level.txt
closeio-2.1.dist-info/RECORD
