Metadata-Version: 2.1
Name: closeio
Version: 2.1
Summary: Close API Python Client
Home-page: https://github.com/closeio/closeio-api/
Author: Close Team
Classifier: Programming Language :: Python
Classifier: Programming Language :: Python :: 3
Classifier: Programming Language :: Python :: 3.7
Classifier: Programming Language :: Python :: 3.8
Classifier: Programming Language :: Python :: 3.9
Classifier: Programming Language :: Python :: 3.10
Classifier: Operating System :: OS Independent
License-File: LICENSE
Requires-Dist: requests (>=2.11.1)
